{
  "description": { "translate": "enchantment.mildlyusefuladditions.reach" },

  "max_level": 3,
  "weight": 3,

  "min_cost": { "base": 15, "per_level_above_first": 9 },
  "max_cost": { "base": 65, "per_level_above_first": 9 },
  "anvil_cost": 4,

  "slots": ["mainhand"],
  "exclusive_set": "#mildlyusefuladditions:exclusive_set/reach",
  "supported_items": "#mildlyusefuladditions:enchantable/reach_tools",
  "primary_items":  "#mildlyusefuladditions:enchantable/reach_tools",

  "effects": {
    "minecraft:attributes": [
      {
        "attribute": "minecraft:player.block_interaction_range",
        "id": "mildlyusefuladditions:reach_block_range",
        "operation": "add_value",
        "amount": {
          "type": "minecraft:linear",
          "base": 0.5,
          "per_level_above_first": 0.5
        }
      },
      {
        "attribute": "minecraft:player.entity_interaction_range",
        "id": "mildlyusefuladditions:reach_entity_range",
        "operation": "add_value",
        "amount": {
          "type": "minecraft:linear",
          "base": 0.5,
          "per_level_above_first": 0.5
        }
      }
    ]
  }
}
